py_queue_bus/__init__.py
py_queue_bus/bus.py
py_queue_bus/rider.py
py_queue_bus/scheduler.py
py_queue_bus/utils.py
py_queue_bus-0.1.2.dist-info/licenses/LICENSE
py_queue_bus-0.1.2.dist-info/METADATA
py_queue_bus-0.1.2.dist-info/WHEEL
py_queue_bus-0.1.2.dist-info/top_level.txt
py_queue_bus-0.1.2.dist-info/RECORD
