Metadata-Version: 2.4
Name: py-queue-bus
Version: 0.1.2
Summary: Python port of queue-bus compatible with node-queue-bus and resque-bus
Author: Siddhanth Bhimakari
License: MIT License
Project-URL: Homepage, https://pypi.org/project/py-queue-bus/
Project-URL: Source, https://github.com/SiddhanthNB/py-queue-bus
Classifier: License :: OSI Approved :: MIT License
Classifier: Programming Language :: Python :: 3
Classifier: Programming Language :: Python :: 3.9
Classifier: Programming Language :: Python :: 3.10
Classifier: Programming Language :: Python :: 3.11
Classifier: Programming Language :: Python :: 3.12
Classifier: Programming Language :: Python :: 3.13
Classifier: Programming Language :: Python :: 3.14
Requires-Python: >=3.9
License-File: LICENSE
Requires-Dist: redis>=5.0
Requires-Dist: rq>=1.15
Requires-Dist: tzlocal>=5.0
Provides-Extra: dev
Requires-Dist: pytest>=8.0; extra == "dev"
Requires-Dist: fakeredis>=2.23.0; extra == "dev"
Requires-Dist: build>=1.0; extra == "dev"
Requires-Dist: twine>=5.0; extra == "dev"
Dynamic: license-file
